tensorviz/__init__.py
tensorviz/cli.py
tensorviz/graph.py
tensorviz/hook.py
tensorviz/html.py
tensorviz/logger.py
tensorviz/reporter.py
tensorviz/utils.py
tensorviz/templates/report.html.j2
tensorviz-0.1.6.dist-info/METADATA
tensorviz-0.1.6.dist-info/WHEEL
tensorviz-0.1.6.dist-info/entry_points.txt
tensorviz-0.1.6.dist-info/top_level.txt
tensorviz-0.1.6.dist-info/RECORD
