Metadata-Version: 2.4
Name: tensorviz
Version: 0.1.6
Summary: Visualize and debug PyTorch model tensors
Author: Divyansh Saraswat
Requires-Python: >=3.8
Requires-Dist: torch
Requires-Dist: graphviz
Requires-Dist: rich
Requires-Dist: jinja2
Requires-Dist: typer
Requires-Dist: torchview
